aidial_client/__init__.py
aidial_client/_auth.py
aidial_client/_client.py
aidial_client/_client_pool.py
aidial_client/_compatibility/__init__.py
aidial_client/_compatibility/openai.py
aidial_client/_compatibility/pydantic.py
aidial_client/_compatibility/pydantic_v1.py
aidial_client/_constants.py
aidial_client/_exception.py
aidial_client/_http_client/__init__.py
aidial_client/_http_client/_async.py
aidial_client/_http_client/_base.py
aidial_client/_http_client/_sync.py
aidial_client/_internal_types/__init__.py
aidial_client/_internal_types/_defaults.py
aidial_client/_internal_types/_generic.py
aidial_client/_internal_types/_http_request.py
aidial_client/_internal_types/_model.py
aidial_client/_log.py
aidial_client/_utils/__init__.py
aidial_client/_utils/_alias.py
aidial_client/_utils/_dict.py
aidial_client/_utils/_openai.py
aidial_client/_utils/_response_processing.py
aidial_client/_utils/_type_guard.py
aidial_client/helpers/__init__.py
aidial_client/helpers/_url.py
aidial_client/helpers/storage_resource.py
aidial_client/resources/__init__.py
aidial_client/resources/application.py
aidial_client/resources/base.py
aidial_client/resources/bucket.py
aidial_client/resources/chat/__init__.py
aidial_client/resources/chat/completions.py
aidial_client/resources/deployments.py
aidial_client/resources/files.py
aidial_client/resources/metadata.py
aidial_client/types/__init__.py
aidial_client/types/application.py
aidial_client/types/bucket.py
aidial_client/types/chat/__init__.py
aidial_client/types/chat/addon.py
aidial_client/types/chat/function.py
aidial_client/types/chat/legacy/__init__.py
aidial_client/types/chat/legacy/application_request.py
aidial_client/types/chat/legacy/chat_completion.py
aidial_client/types/chat/request.py
aidial_client/types/chat/request_param.py
aidial_client/types/chat/response.py
aidial_client/types/chat/tool.py
aidial_client/types/deployment.py
aidial_client/types/file.py
aidial_client/types/metadata.py
aidial_client-0.4.0.dist-info/LICENSE
aidial_client-0.4.0.dist-info/METADATA
aidial_client-0.4.0.dist-info/WHEEL
aidial_client-0.4.0.dist-info/RECORD
